eightbitALU/multiplier.v
module shift_mult_8bit (
    input  [7:0] a, 
    input  [7:0] b, 
    output [15:0] prod
);
    wire [15:0] a_ext = {8'b0, a};
    
    wire [15:0] stage1, stage2, stage3, stage4;

    assign stage1 = b[0] ? (a_ext << 1) : a_ext;

    assign stage2 = b[1] ? (stage1 << 2) : stage1;

    assign stage3 = b[2] ? (stage2 << 4) : stage2;

    assign stage4 = b[3] ? (stage3 << 8) : stage3;

    assign prod = stage4;

endmodule

eightbitALU/Sources/fulladder.v
module half_adder (
    input a, 
    input b, 
    output sum, 
    output carry
);
    assign sum   = a ^ b;
    assign carry = a & b; 
endmodule

module full_adder (
    input a, 
    input b, 
    input cin, 
    output sum, 
    output cout
);
    wire s1, c1, c2;
    
    half_adder ha1 (.a(a),  .b(b),   .sum(s1),  .carry(c1));
    half_adder ha2 (.a(s1), .b(cin), .sum(sum), .carry(c2));
    
    assign cout = c1 | c2;
endmodule

eightbitALU/Sources/eightbitadder.v
module rca_8bit (
    input  [7:0] a, 
    input  [7:0] b, 
    input        cin, 
    output [7:0] sum, 
    output       cout
);
    wire c1, c2, c3, c4, c5, c6, c7;
    
    full_adder fa0 (.a(a[0]), .b(b[0]), .cin(cin), .sum(sum[0]), .cout(c1));
    full_adder fa1 (.a(a[1]), .b(b[1]), .cin(c1),  .sum(sum[1]), .cout(c2));
    full_adder fa2 (.a(a[2]), .b(b[2]), .cin(c2),  .sum(sum[2]), .cout(c3));
    full_adder fa3 (.a(a[3]), .b(b[3]), .cin(c3),  .sum(sum[3]), .cout(c4));
    full_adder fa4 (.a(a[4]), .b(b[4]), .cin(c4),  .sum(sum[4]), .cout(c5));
    full_adder fa5 (.a(a[5]), .b(b[5]), .cin(c5),  .sum(sum[5]), .cout(c6));
    full_adder fa6 (.a(a[6]), .b(b[6]), .cin(c6),  .sum(sum[6]), .cout(c7));
    full_adder fa7 (.a(a[7]), .b(b[7]), .cin(c7),  .sum(sum[7]), .cout(cout));
endmodule

eightbitALU/Sources/eightbitsubtractor.v
module sub_8bit (
    input  [7:0] a, 
    input  [7:0] b, 
    output [7:0] diff, 
    output       bout
);
    wire [7:0] b_inv;
    assign b_inv = ~b; 
    
    // A - B = A + (~B) + 1
    rca_8bit subtractor (
        .a(a), 
        .b(b_inv), 
        .cin(1'b1), 
        .sum(diff), 
        .cout(bout)
    );
endmodule

eightbitALU/top.v
module alu_top (
    input  [7:0] a, 
    input  [7:0] b, 
    input  [2:0] sel, 
    output reg [15:0] result
);
    wire [7:0] sum_out, diff_out;
    wire [15:0] mult_out;
    wire cout, bout;

    rca_8bit        adder      (.a(a), .b(b), .cin(1'b0), .sum(sum_out), .cout(cout));
    sub_8bit        subtractor (.a(a), .b(b), .diff(diff_out), .bout(bout));
    shift_mult_8bit shifter    (.a(a), .b(b), .prod(mult_out));


    always @(*) begin
        case (sel)
            3'b000: result = sum_out;  
            3'b001: result = diff_out; 
            3'b010: result = mult_out;
            3'b011: result = a & b;
            3'b100: result = a | b;
            3'b101: result = a ^ b;
            3'b110: result = ~ (a & b);
            3'b111: result = ~ (a | b);         
            default: result = 16'b0;
        endcase
    end
endmodule

eightbitALU/tb.v
`timescale 1ns / 1ps

module tb_alu;
    reg [7:0] a;
    reg [7:0] b;
    reg [2:0] sel;

    wire [15:0] result;

    alu_top uut (
        .a(a), 
        .b(b), 
        .sel(sel), 
        .result(result)
    );

    initial begin
        a = 8'd25;   b = 8'd10;   sel = 3'b000;
        #10;
        $display("ADD    : %d + %d = %d", a, b, result);

        a = 8'd50;   b = 8'd15;   sel = 3'b001;
        #10;
        $display("SUB    : %d - %d = %d", a, b, result);

        // 3 * (2^8) = 3 * 256 = 768
        a = 8'd3;    b = 8'd8;    sel = 3'b010;
        #10;
        $display("2^n MUL: %d * 2^%d = %d", a, b, result);

        a = 8'd50;   b = 8'd15;   sel = 3'b011;
        #10;
        $display("AND    : %d AND %d = %d", a, b, result);

        a = 8'd50;   b = 8'd15;   sel = 3'b100;
        #10;
        $display("OR    : %d OR %d = %d", a, b, result);

        a = 8'd50;   b = 8'd15;   sel = 3'b101;
        #10;
        $display("XOR    : %d XOR %d = %d", a, b, result);

        a = 8'd50;   b = 8'd15;   sel = 3'b110;
        #10;
        $display("NAND    : %d NAND %d = %d", a, b, result);

        a = 8'd50;   b = 8'd15;   sel = 3'b111;
        #10;
        $display("NOR    : %d NOR %d = %d", a, b, result);



        $finish;
    end
endmodule

eightbitALU/alu.vcd
$date
	Tue Jun 30 22:05:01 2026
$end
$version
	Icarus Verilog
$end
$timescale
	1ps
$end
$scope module tb_alu $end
$var wire 16 ! result [15:0] $end
$var reg 8 " a [7:0] $end
$var reg 8 # b [7:0] $end
$var reg 3 $ sel [2:0] $end
$scope module uut $end
$var wire 8 % a [7:0] $end
$var wire 8 & b [7:0] $end
$var wire 3 ' sel [2:0] $end
$var wire 8 ( sum_out [7:0] $end
$var wire 16 ) mult_out [15:0] $end
$var wire 8 * diff_out [7:0] $end
$var wire 1 + cout $end
$var wire 1 , bout $end
$var reg 16 - result [15:0] $end
$scope module adder $end
$var wire 8 . a [7:0] $end
$var wire 8 / b [7:0] $end
$var wire 1 0 cin $end
$var wire 8 1 sum [7:0] $end
$var wire 1 + cout $end
$var wire 1 2 c7 $end
$var wire 1 3 c6 $end
$var wire 1 4 c5 $end
$var wire 1 5 c4 $end
$var wire 1 6 c3 $end
$var wire 1 7 c2 $end
$var wire 1 8 c1 $end
$scope module fa0 $end
$var wire 1 9 a $end
$var wire 1 : b $end
$var wire 1 0 cin $end
$var wire 1 8 cout $end
$var wire 1 ; sum $end
$var wire 1 < s1 $end
$var wire 1 = c2 $end
$var wire 1 > c1 $end
$scope module ha1 $end
$var wire 1 9 a $end
$var wire 1 : b $end
$var wire 1 > carry $end
$var wire 1 < sum $end
$upscope $end
$scope module ha2 $end
$var wire 1 < a $end
$var wire 1 0 b $end
$var wire 1 = carry $end
$var wire 1 ; sum $end
$upscope $end
$upscope $end
$scope module fa1 $end
$var wire 1 ? a $end
$var wire 1 @ b $end
$var wire 1 8 cin $end
$var wire 1 7 cout $end
$var wire 1 A sum $end
$var wire 1 B s1 $end
$var wire 1 C c2 $end
$var wire 1 D c1 $end
$scope module ha1 $end
$var wire 1 ? a $end
$var wire 1 @ b $end
$var wire 1 D carry $end
$var wire 1 B sum $end
$upscope $end
$scope module ha2 $end
$var wire 1 B a $end
$var wire 1 8 b $end
$var wire 1 C carry $end
$var wire 1 A sum $end
$upscope $end
$upscope $end
$scope module fa2 $end
$var wire 1 E a $end
$var wire 1 F b $end
$var wire 1 7 cin $end
$var wire 1 6 cout $end
$var wire 1 G sum $end
$var wire 1 H s1 $end
$var wire 1 I c2 $end
$var wire 1 J c1 $end
$scope module ha1 $end
$var wire 1 E a $end
$var wire 1 F b $end
$var wire 1 J carry $end
$var wire 1 H sum $end
$upscope $end
$scope module ha2 $end
$var wire 1 H a $end
$var wire 1 7 b $end
$var wire 1 I carry $end
$var wire 1 G sum $end
$upscope $end
$upscope $end
$scope module fa3 $end
$var wire 1 K a $end
$var wire 1 L b $end
$var wire 1 6 cin $end
$var wire 1 5 cout $end
$var wire 1 M sum $end
$var wire 1 N s1 $end
$var wire 1 O c2 $end
$var wire 1 P c1 $end
$scope module ha1 $end
$var wire 1 K a $end
$var wire 1 L b $end
$var wire 1 P carry $end
$var wire 1 N sum $end
$upscope $end
$scope module ha2 $end
$var wire 1 N a $end
$var wire 1 6 b $end
$var wire 1 O carry $end
$var wire 1 M sum $end
$upscope $end
$upscope $end
$scope module fa4 $end
$var wire 1 Q a $end
$var wire 1 R b $end
$var wire 1 5 cin $end
$var wire 1 4 cout $end
$var wire 1 S sum $end
$var wire 1 T s1 $end
$var wire 1 U c2 $end
$var wire 1 V c1 $end
$scope module ha1 $end
$var wire 1 Q a $end
$var wire 1 R b $end
$var wire 1 V carry $end
$var wire 1 T sum $end
$upscope $end
$scope module ha2 $end
$var wire 1 T a $end
$var wire 1 5 b $end
$var wire 1 U carry $end
$var wire 1 S sum $end
$upscope $end
$upscope $end
$scope module fa5 $end
$var wire 1 W a $end
$var wire 1 X b $end
$var wire 1 4 cin $end
$var wire 1 3 cout $end
$var wire 1 Y sum $end
$var wire 1 Z s1 $end
$var wire 1 [ c2 $end
$var wire 1 \ c1 $end
$scope module ha1 $end
$var wire 1 W a $end
$var wire 1 X b $end
$var wire 1 \ carry $end
$var wire 1 Z sum $end
$upscope $end
$scope module ha2 $end
$var wire 1 Z a $end
$var wire 1 4 b $end
$var wire 1 [ carry $end
$var wire 1 Y sum $end
$upscope $end
$upscope $end
$scope module fa6 $end
$var wire 1 ] a $end
$var wire 1 ^ b $end
$var wire 1 3 cin $end
$var wire 1 2 cout $end
$var wire 1 _ sum $end
$var wire 1 ` s1 $end
$var wire 1 a c2 $end
$var wire 1 b c1 $end
$scope module ha1 $end
$var wire 1 ] a $end
$var wire 1 ^ b $end
$var wire 1 b carry $end
$var wire 1 ` sum $end
$upscope $end
$scope module ha2 $end
$var wire 1 ` a $end
$var wire 1 3 b $end
$var wire 1 a carry $end
$var wire 1 _ sum $end
$upscope $end
$upscope $end
$scope module fa7 $end
$var wire 1 c a $end
$var wire 1 d b $end
$var wire 1 2 cin $end
$var wire 1 + cout $end
$var wire 1 e sum $end
$var wire 1 f s1 $end
$var wire 1 g c2 $end
$var wire 1 h c1 $end
$scope module ha1 $end
$var wire 1 c a $end
$var wire 1 d b $end
$var wire 1 h carry $end
$var wire 1 f sum $end
$upscope $end
$scope module ha2 $end
$var wire 1 f a $end
$var wire 1 2 b $end
$var wire 1 g carry $end
$var wire 1 e sum $end
$upscope $end
$upscope $end
$upscope $end
$scope module shifter $end
$var wire 8 i a [7:0] $end
$var wire 8 j b [7:0] $end
$var wire 16 k prod [15:0] $end
$var wire 16 l stage4 [15:0] $end
$var wire 16 m stage3 [15:0] $end
$var wire 16 n stage2 [15:0] $end
$var wire 16 o stage1 [15:0] $end
$var wire 16 p a_ext [15:0] $end
$upscope $end
$scope module subtractor $end
$var wire 8 q a [7:0] $end
$var wire 8 r b [7:0] $end
$var wire 8 s b_inv [7:0] $end
$var wire 8 t diff [7:0] $end
$var wire 1 , bout $end
$scope module subtractor $end
$var wire 8 u a [7:0] $end
$var wire 8 v b [7:0] $end
$var wire 1 w cin $end
$var wire 8 x sum [7:0] $end
$var wire 1 , cout $end
$var wire 1 y c7 $end
$var wire 1 z c6 $end
$var wire 1 { c5 $end
$var wire 1 | c4 $end
$var wire 1 } c3 $end
$var wire 1 ~ c2 $end
$var wire 1 !" c1 $end
$scope module fa0 $end
$var wire 1 "" a $end
$var wire 1 #" b $end
$var wire 1 w cin $end
$var wire 1 !" cout $end
$var wire 1 $" sum $end
$var wire 1 %" s1 $end
$var wire 1 &" c2 $end
$var wire 1 '" c1 $end
$scope module ha1 $end
$var wire 1 "" a $end
$var wire 1 #" b $end
$var wire 1 '" carry $end
$var wire 1 %" sum $end
$upscope $end
$scope module ha2 $end
$var wire 1 %" a $end
$var wire 1 w b $end
$var wire 1 &" carry $end
$var wire 1 $" sum $end
$upscope $end
$upscope $end
$scope module fa1 $end
$var wire 1 (" a $end
$var wire 1 )" b $end
$var wire 1 !" cin $end
$var wire 1 ~ cout $end
$var wire 1 *" sum $end
$var wire 1 +" s1 $end
$var wire 1 ," c2 $end
$var wire 1 -" c1 $end
$scope module ha1 $end
$var wire 1 (" a $end
$var wire 1 )" b $end
$var wire 1 -" carry $end
$var wire 1 +" sum $end
$upscope $end
$scope module ha2 $end
$var wire 1 +" a $end
$var wire 1 !" b $end
$var wire 1 ," carry $end
$var wire 1 *" sum $end
$upscope $end
$upscope $end
$scope module fa2 $end
$var wire 1 ." a $end
$var wire 1 /" b $end
$var wire 1 ~ cin $end
$var wire 1 } cout $end
$var wire 1 0" sum $end
$var wire 1 1" s1 $end
$var wire 1 2" c2 $end
$var wire 1 3" c1 $end
$scope module ha1 $end
$var wire 1 ." a $end
$var wire 1 /" b $end
$var wire 1 3" carry $end
$var wire 1 1" sum $end
$upscope $end
$scope module ha2 $end
$var wire 1 1" a $end
$var wire 1 ~ b $end
$var wire 1 2" carry $end
$var wire 1 0" sum $end
$upscope $end
$upscope $end
$scope module fa3 $end
$var wire 1 4" a $end
$var wire 1 5" b $end
$var wire 1 } cin $end
$var wire 1 | cout $end
$var wire 1 6" sum $end
$var wire 1 7" s1 $end
$var wire 1 8" c2 $end
$var wire 1 9" c1 $end
$scope module ha1 $end
$var wire 1 4" a $end
$var wire 1 5" b $end
$var wire 1 9" carry $end
$var wire 1 7" sum $end
$upscope $end
$scope module ha2 $end
$var wire 1 7" a $end
$var wire 1 } b $end
$var wire 1 8" carry $end
$var wire 1 6" sum $end
$upscope $end
$upscope $end
$scope module fa4 $end
$var wire 1 :" a $end
$var wire 1 ;" b $end
$var wire 1 | cin $end
$var wire 1 { cout $end
$var wire 1 <" sum $end
$var wire 1 =" s1 $end
$var wire 1 >" c2 $end
$var wire 1 ?" c1 $end
$scope module ha1 $end
$var wire 1 :" a $end
$var wire 1 ;" b $end
$var wire 1 ?" carry $end
$var wire 1 =" sum $end
$upscope $end
$scope module ha2 $end
$var wire 1 =" a $end
$var wire 1 | b $end
$var wire 1 >" carry $end
$var wire 1 <" sum $end
$upscope $end
$upscope $end
$scope module fa5 $end
$var wire 1 @" a $end
$var wire 1 A" b $end
$var wire 1 { cin $end
$var wire 1 z cout $end
$var wire 1 B" sum $end
$var wire 1 C" s1 $end
$var wire 1 D" c2 $end
$var wire 1 E" c1 $end
$scope module ha1 $end
$var wire 1 @" a $end
$var wire 1 A" b $end
$var wire 1 E" carry $end
$var wire 1 C" sum $end
$upscope $end
$scope module ha2 $end
$var wire 1 C" a $end
$var wire 1 { b $end
$var wire 1 D" carry $end
$var wire 1 B" sum $end
$upscope $end
$upscope $end
$scope module fa6 $end
$var wire 1 F" a $end
$var wire 1 G" b $end
$var wire 1 z cin $end
$var wire 1 y cout $end
$var wire 1 H" sum $end
$var wire 1 I" s1 $end
$var wire 1 J" c2 $end
$var wire 1 K" c1 $end
$scope module ha1 $end
$var wire 1 F" a $end
$var wire 1 G" b $end
$var wire 1 K" carry $end
$var wire 1 I" sum $end
$upscope $end
$scope module ha2 $end
$var wire 1 I" a $end
$var wire 1 z b $end
$var wire 1 J" carry $end
$var wire 1 H" sum $end
$upscope $end
$upscope $end
$scope module fa7 $end
$var wire 1 L" a $end
$var wire 1 M" b $end
$var wire 1 y cin $end
$var wire 1 , cout $end
$var wire 1 N" sum $end
$var wire 1 O" s1 $end
$var wire 1 P" c2 $end
$var wire 1 Q" c1 $end
$scope module ha1 $end
$var wire 1 L" a $end
$var wire 1 M" b $end
$var wire 1 Q" carry $end
$var wire 1 O" sum $end
$upscope $end
$scope module ha2 $end
$var wire 1 O" a $end
$var wire 1 y b $end
$var wire 1 P" carry $end
$var wire 1 N" sum $end
$upscope $end
$upscope $end
$upscope $end
$upscope $end
$upscope $end
$upscope $end
$enddefinitions $end
$comment Show the parameter values. $end
$dumpall
$end
#0
$dumpvars
0Q"
1P"
1O"
0N"
1M"
0L"
0K"
1J"
1I"
0H"
1G"
0F"
0E"
1D"
1C"
0B"
1A"
0@"
1?"
0>"
0="
0<"
1;"
1:"
09"
08"
17"
16"
05"
14"
03"
02"
11"
10"
1/"
0."
0-"
0,"
0+"
1*"
0)"
0("
1'"
0&"
0%"
1$"
1#"
1""
1!"
0~
0}
0|
1{
1z
1y
b1111 x
1w
b11110101 v
b11001 u
b1111 t
b11110101 s
b1010 r
b11001 q
b11001 p
b11001 o
b1100100 n
b1100100 m
b110010000000000 l
b110010000000000 k
b1010 j
b11001 i
0h
0g
0f
0e
0d
0c
0b
0a
0`
0_
0^
0]
0\
0[
0Z
1Y
0X
0W
0V
1U
1T
0S
0R
1Q
1P
0O
0N
0M
1L
1K
0J
0I
0H
0G
0F
0E
0D
0C
1B
1A
1@
0?
0>
0=
1<
1;
0:
19
08
07
06
15
14
03
02
b100011 1
00
b1010 /
b11001 .
b100011 -
1,
0+
b1111 *
b110010000000000 )
b100011 (
b0 '
b1010 &
b11001 %
b0 $
b1010 #
b11001 "
b100011 !
$end
#10000
00"
1O
14
1_
16
b0 )
b0 k
b0 l
0S
1U
13
0~
1I
01"
0A
17
0M
15
b1000001 (
b1000001 1
0Y
1[
b110010000 n
1$"
0&"
0!"
1*"
0,"
06"
b100011 *
b100011 t
b100011 x
1B"
0D"
1H
b1100100000000 m
0#"
0/"
0B
1D
1N
0P
1Z
0%"
0'"
1+"
07"
0C"
1E"
1:
1F
b11110000 s
b11110000 v
09
1?
0K
1W
b1100100 o
0""
1("
04"
1@"
b100011 !
b100011 -
b1 $
b1 '
b1111 #
b1111 &
b1111 /
b1111 j
b1111 r
b110010 p
b110010 "
b110010 %
b110010 .
b110010 i
b110010 q
b110010 u
#20000
16"
0,
05
1}
1N"
0P"
1M
0O
12"
0_
0y
06
b1100000000 )
b1100000000 k
b1100000000 l
1~
00"
04
03
1!"
1H"
0J"
1A
07
0G
0I
1'"
0+"
1-"
11"
0S
0U
b1011 (
b1011 1
0Y
0[
1$"
0&"
1<"
0{
b11111011 *
b11111011 t
b11111011 x
1B"
0D"
0z
1B
0D
0H
b11 n
b11 m
1#"
1)"
1/"
0T
0Z
b11 o
0%"
1="
0?"
1C"
0E"
0:
0@
0F
b11110111 s
b11110111 v
19
0Q
0W
1""
0:"
0@"
b1100000000 !
b1100000000 -
b10 $
b10 '
b1000 #
b1000 &
b1000 /
b1000 j
b1000 r
b11 p
b11 "
b11 %
b11 .
b11 i
b11 q
b11 u
#30000
1_
13
1[
14
1U
15
1,
0M
1O
06"
0N"
1P"
16
0}
1*"
0,"
1y
1I
b0 )
b0 k
b0 l
0~
00"
02"
0H"
1J"
0A
17
0G
1+"
0-"
01"
0S
b1000001 (
b1000001 1
0Y
1$"
0&"
0!"
0<"
1{
b100011 *
b100011 t
b100011 x
1B"
1z
0B
1D
1H
b1100100000000 m
0#"
0)"
0/"
1T
1Z
b110010000 n
0%"
0'"
0="
1?"
0C"
1E"
1:
1@
1F
b11110000 s
b11110000 v
09
1Q
1W
b1100100 o
0""
1:"
1@"
b10 !
b10 -
b11 $
b11 '
b1111 #
b1111 &
b1111 /
b1111 j
b1111 r
b110010 p
b110010 "
b110010 %
b110010 .
b110010 i
b110010 q
b110010 u
#40000
b111111 !
b111111 -
b100 $
b100 '
#50000
b111101 !
b111101 -
b101 $
b101 '
#60000
b1111111111111101 !
b1111111111111101 -
b110 $
b110 '
#70000
b1111111111000000 !
b1111111111000000 -
b111 $
b111 '
